dask_databricks/__init__.py
dask_databricks/_version.py
dask_databricks/cli.py
dask_databricks/databrickscluster.py
dask_databricks/tests/test_databricks.py
dask_databricks-0.3.2.dist-info/METADATA
dask_databricks-0.3.2.dist-info/WHEEL
dask_databricks-0.3.2.dist-info/entry_points.txt
dask_databricks-0.3.2.dist-info/licenses/LICENSE
dask_databricks-0.3.2.dist-info/RECORD
