Metadata-Version: 2.3
Name: dask-databricks
Version: 0.3.2
Project-URL: Documentation, https://github.com/dask-contrib/dask-databricks#readme
Project-URL: Issues, https://github.com/dask-contrib/dask-databricks/issues
Project-URL: Source, https://github.com/dask-contrib/dask-databricks
Author-email: Jacob Tomlinson <jacob@tomlinson.email>
License: BSD-3-Clause
License-File: LICENSE
Classifier: Development Status :: 4 - Beta
Classifier: Programming Language :: Python
Classifier: Programming Language :: Python :: 3.9
Classifier: Programming Language :: Python :: 3.10
Classifier: Programming Language :: Python :: 3.11
Classifier: Programming Language :: Python :: Implementation :: CPython
Classifier: Programming Language :: Python :: Implementation :: PyPy
Requires-Python: >=3.9
Requires-Dist: bokeh<=3.2.2
Requires-Dist: click>=8.1
Requires-Dist: dask
Requires-Dist: distributed
Requires-Dist: rich
